DataAnalysis_Package/Data_PreProcessing.py
DataAnalysis_Package/Data_Visualization.py
DataAnalysis_Package/ML_MODELS.py
DataAnalysis_Package/Statistical_Analysis.py
DataAnalysis_Package/__init__.py
LnT_HR_AI-0.0.7.dist-info/METADATA
LnT_HR_AI-0.0.7.dist-info/WHEEL
LnT_HR_AI-0.0.7.dist-info/entry_points.txt
LnT_HR_AI-0.0.7.dist-info/top_level.txt
LnT_HR_AI-0.0.7.dist-info/RECORD
